README.md
setup.py
sa_insert_helper/__init__.py
sa_insert_helper/insert.py
sa_insert_helper.egg-info/PKG-INFO
sa_insert_helper.egg-info/SOURCES.txt
sa_insert_helper.egg-info/dependency_links.txt
sa_insert_helper.egg-info/top_level.txt