Metadata-Version: 1.0
Name: sa-insert-helper
Version: 0.0.1
Summary: a library for bulk insert
Home-page: https://github.com/sunurdy/sa_insert_helper
Author: sunurdy
Author-email: sunurdy@hotmail.com
License: MIT License
Keywords: bulk insert
Platform: UNKNOWN
